lonny_aws_blob/__init__.py
lonny_aws_blob/blob.py
lonny_aws_blob/configuration.py
lonny_aws_blob/lock.py
lonny_aws_blob/logger.py
lonny_aws_blob-0.1.2.dist-info/WHEEL
lonny_aws_blob-0.1.2.dist-info/METADATA
lonny_aws_blob-0.1.2.dist-info/RECORD
